odoo10_addon_document_page_partner_id-10.0.1.0.0.99.dev4-py3.8-nspkg.pth
odoo/addons/document_page_partner_id/README.rst
odoo/addons/document_page_partner_id/__init__.py
odoo/addons/document_page_partner_id/__manifest__.py
odoo/addons/document_page_partner_id/i18n/document_page_partner_id.pot
odoo/addons/document_page_partner_id/models/__init__.py
odoo/addons/document_page_partner_id/models/document_page.py
odoo/addons/document_page_partner_id/readme/CONTRIBUTORS.rst
odoo/addons/document_page_partner_id/readme/DESCRIPTION.rst
odoo/addons/document_page_partner_id/readme/USAGE.rst
odoo/addons/document_page_partner_id/static/description/icon.png
odoo/addons/document_page_partner_id/static/description/index.html
odoo/addons/document_page_partner_id/views/document_page.xml
odoo10_addon_document_page_partner_id-10.0.1.0.0.99.dev4.dist-info/METADATA
odoo10_addon_document_page_partner_id-10.0.1.0.0.99.dev4.dist-info/WHEEL
odoo10_addon_document_page_partner_id-10.0.1.0.0.99.dev4.dist-info/namespace_packages.txt
odoo10_addon_document_page_partner_id-10.0.1.0.0.99.dev4.dist-info/top_level.txt
odoo10_addon_document_page_partner_id-10.0.1.0.0.99.dev4.dist-info/RECORD
